pyfindmaxima-0.1.1.1.dist-info/LICENSE
pyfindmaxima-0.1.1.1.dist-info/RECORD
pyfindmaxima-0.1.1.1.dist-info/top_level.txt
pyfindmaxima-0.1.1.1.dist-info/METADATA
pyfindmaxima-0.1.1.1.dist-info/WHEEL
findmaxima/findmaxima.py
findmaxima/cy_findmaxima.pyx
findmaxima/__init__.py
findmaxima/cy_findmaxima.cpython-39-i386-linux-gnu.so
